{
    "purim": [
        {
            "id": "7Ki4LZ3N3Z8",
            "title": "מחרוזת שירי פורים ברצף עם רינת גבאי - פורים בערוץ בייבי",
            "url": "https://www.youtube.com/embed/7Ki4LZ3N3Z8?rel=0",
            "lesson_plan": "פעילות רעשנים: מחלקים רעשנים ומרעישים לפי קצב השיר. בבתים שקטים עוצרים ובפזמון מרעישים חזק."
        },
        {
            "id": "cJtzNaS2tX4",
            "title": "מחרוזת שירי פורים לילדים - שירי ילדות אהובים -  ילדות ישראלית",
            "url": "https://www.youtube.com/embed/cJtzNaS2tX4?rel=0",
            "lesson_plan": "פעילות רעשנים: מחלקים רעשנים ומרעישים לפי קצב השיר. בבתים שקטים עוצרים ובפזמון מרעישים חזק."
        },
        {
            "id": "r6QT2S0aljo",
            "title": "איציק אשל - מחרוזת שיריי פורים",
            "url": "https://www.youtube.com/embed/r6QT2S0aljo?rel=0",
            "lesson_plan": "פעילות רעשנים: מחלקים רעשנים ומרעישים לפי קצב השיר. בבתים שקטים עוצרים ובפזמון מרעישים חזק."
        },
        {
            "id": "PJLjX-rdf-Q",
            "title": "שירי פורים ברצף - שירי פורים -  שירים לכל המשפחה",
            "url": "https://www.youtube.com/embed/PJLjX-rdf-Q?rel=0",
            "lesson_plan": "פעילות רעשנים: מחלקים רעשנים ומרעישים לפי קצב השיר. בבתים שקטים עוצרים ובפזמון מרעישים חזק."
        },
        {
            "id": "8HSYzUIQMYU",
            "title": "שירי פורים לילדים ולגננות",
            "url": "https://www.youtube.com/embed/8HSYzUIQMYU?rel=0",
            "lesson_plan": "פעילות רעשנים: מחלקים רעשנים ומרעישים לפי קצב השיר. בבתים שקטים עוצרים ובפזמון מרעישים חזק."
        },
        {
            "id": "9i5gHVLInuI",
            "title": "מחרוזת פורים I קינדרלעך Purim Medley I Kinderlach 2014",
            "url": "https://www.youtube.com/embed/9i5gHVLInuI?rel=0",
            "lesson_plan": "פעילות רעשנים: מחלקים רעשנים ומרעישים לפי קצב השיר. בבתים שקטים עוצרים ובפזמון מרעישים חזק."
        },
        {
            "id": "LFrvM2vvoDI",
            "title": "ילדות ישראלית - ספיישל פורים שמח - שירי ילדים ברצף - שירי פורים לילדים",
            "url": "https://www.youtube.com/embed/LFrvM2vvoDI?rel=0",
            "lesson_plan": "פעילות רעשנים: מחלקים רעשנים ומרעישים לפי קצב השיר. בבתים שקטים עוצרים ובפזמון מרעישים חזק."
        },
        {
            "id": "HHZOfcT66OU",
            "title": "אני פורים - שירי פורים ברצף",
            "url": "https://www.youtube.com/embed/HHZOfcT66OU?rel=0",
            "lesson_plan": "פעילות רעשנים: מחלקים רעשנים ומרעישים לפי קצב השיר. בבתים שקטים עוצרים ובפזמון מרעישים חזק."
        },
        {
            "id": "I62vpwtDXQk",
            "title": "מחרוזת פורים - שירי חג פורים - שרי פופ",
            "url": "https://www.youtube.com/embed/I62vpwtDXQk?rel=0",
            "lesson_plan": "ריקוד פורים: עומדים במעגל, מתחפשים בדמיון וצועדים לפי המקצב. בכל פעם שמוזכרת דמות מהחג מבצעים תנועה אופיינית."
        },
        {
            "id": "txFRNYcTwQk",
            "title": "שירי חג פורים לשמיעה ברצף- עם רעותי כוכבת הילדים, 17 דקות",
            "url": "https://www.youtube.com/embed/txFRNYcTwQk?rel=0",
            "lesson_plan": "פעילות רעשנים: מחלקים רעשנים ומרעישים לפי קצב השיר. בבתים שקטים עוצרים ובפזמון מרעישים חזק."
        },
        {
            "id": "VEzqrB_Dyts",
            "title": "שושנת יעקב - שירי פורים - ילדות ישראלית",
            "url": "https://www.youtube.com/embed/VEzqrB_Dyts?rel=0",
            "lesson_plan": "ריקוד פורים: עומדים במעגל, מתחפשים בדמיון וצועדים לפי המקצב. בכל פעם שמוזכרת דמות מהחג מבצעים תנועה אופיינית."
        },
        {
            "id": "eIY_zsSenC0",
            "title": "מסכות (לכבוד פורים) - לחן: אברהם גולדפאדן, עממי / ביצוע: ליצני החצר (1977)",
            "url": "https://www.youtube.com/embed/eIY_zsSenC0?rel=0",
            "lesson_plan": "פעילות רעשנים: מחלקים רעשנים ומרעישים לפי קצב השיר. בבתים שקטים עוצרים ובפזמון מרעישים חזק."
        }
    ],
    "morning_circle": [
        {
            "id": "3A604XXfo6c",
            "title": "שירי בוקר לילדים - מחרוזת שירי ילדים ברצף - ילדות ישראלית",
            "url": "https://www.youtube.com/embed/3A604XXfo6c?rel=0",
            "lesson_plan": "פעילות גוף: נוגעים באיברי הגוף המוזכרים בשיר ומבצעים מתיחות בוקר עדינות."
        },
        {
            "id": "JJntrgjnTWk",
            "title": "שירי בוקר לילדים - מחרוזת שירי ילדים ברצף 2024 - ילדות ישראלית",
            "url": "https://www.youtube.com/embed/JJntrgjnTWk?rel=0",
            "lesson_plan": "מפגש בוקר: יושבים במעגל. כל ילד מברך את החבר שלידו ב'בוקר טוב' עם תנועת יד תואמת לשיר."
        },
        {
            "id": "RAbDQApVHBk",
            "title": "בוקר טוב - שיר ילדים - שירי ערוץ בייבי",
            "url": "https://www.youtube.com/embed/RAbDQApVHBk?rel=0",
            "lesson_plan": "מפגש בוקר: יושבים במעגל. כל ילד מברך את החבר שלידו ב'בוקר טוב' עם תנועת יד תואמת לשיר."
        },
        {
            "id": "ZrQWEiVG6nU",
            "title": "הי בוקר טוב מירב האוסמן // חוויה מוסיקלית",
            "url": "https://www.youtube.com/embed/ZrQWEiVG6nU?rel=0",
            "lesson_plan": "מפגש בוקר: יושבים במעגל. כל ילד מברך את החבר שלידו ב'בוקר טוב' עם תנועת יד תואמת לשיר."
        },
        {
            "id": "chwKP7gWLUo",
            "title": "שרים בדרך לגן- מחרוזת שירי חזרה לגן ולבית הספר בילדות ישראלית",
            "url": "https://www.youtube.com/embed/chwKP7gWLUo?rel=0",
            "lesson_plan": "פעילות גוף: נוגעים באיברי הגוף המוזכרים בשיר ומבצעים מתיחות בוקר עדינות."
        },
        {
            "id": "ZD6OXOEQ5Sw",
            "title": "מחרוזת שירים שקטים ורגועים - שירים ברצף - ילדות ישראלית",
            "url": "https://www.youtube.com/embed/ZD6OXOEQ5Sw?rel=0",
            "lesson_plan": "מפגש בוקר: יושבים במעגל. כל ילד מברך את החבר שלידו ב'בוקר טוב' עם תנועת יד תואמת לשיר."
        },
        {
            "id": "oCiAabrMats",
            "title": "שירי בוקר לילדים ולפעוטות - שירי בוקר טוב - ערוץ לולי",
            "url": "https://www.youtube.com/embed/oCiAabrMats?rel=0",
            "lesson_plan": "מפגש בוקר: יושבים במעגל. כל ילד מברך את החבר שלידו ב'בוקר טוב' עם תנועת יד תואמת לשיר."
        },
        {
            "id": "IS0cKfJGc0w",
            "title": "בוקר טוב לגוף שלי",
            "url": "https://www.youtube.com/embed/IS0cKfJGc0w?rel=0",
            "lesson_plan": "מפגש בוקר: יושבים במעגל. כל ילד מברך את החבר שלידו ב'בוקר טוב' עם תנועת יד תואמת לשיר."
        },
        {
            "id": "cDR5VOixG3I",
            "title": "שיר בוקר - שירי ילדות אהובים - ערוץ הופ! לגדול בידיים טובות",
            "url": "https://www.youtube.com/embed/cDR5VOixG3I?rel=0",
            "lesson_plan": "מפגש בוקר: יושבים במעגל. כל ילד מברך את החבר שלידו ב'בוקר טוב' עם תנועת יד תואמת לשיר."
        },
        {
            "id": "VF-N0xSNFFw",
            "title": "שלום שלום - שיר ילדים - שירי  ילדות ישראלית",
            "url": "https://www.youtube.com/embed/VF-N0xSNFFw?rel=0",
            "lesson_plan": "מפגש בוקר: יושבים במעגל. כל ילד מברך את החבר שלידו ב'בוקר טוב' עם תנועת יד תואמת לשיר."
        },
        {
            "id": "CkGvOv0E9y4",
            "title": "בוקר טוב לחברים - שיר בוקר לילדים עם דגש על חברות - עפרה ועידן - ילד מוזיקה",
            "url": "https://www.youtube.com/embed/CkGvOv0E9y4?rel=0",
            "lesson_plan": "מפגש בוקר: יושבים במעגל. כל ילד מברך את החבר שלידו ב'בוקר טוב' עם תנועת יד תואמת לשיר."
        },
        {
            "id": "EUBJ_waKlKg",
            "title": "בוקר טוב עולם - שיר פעולות בוקר - שיר בוקר לגן ילדים - שיר פתיחה לילדים - עפרה ועידן - ילד מוזיקה",
            "url": "https://www.youtube.com/embed/EUBJ_waKlKg?rel=0",
            "lesson_plan": "מפגש בוקר: יושבים במעגל. כל ילד מברך את החבר שלידו ב'בוקר טוב' עם תנועת יד תואמת לשיר."
        }
    ],
    "movement_play": [
        {
            "id": "ZrQWEiVG6nU",
            "title": "הי בוקר טוב מירב האוסמן // חוויה מוסיקלית",
            "url": "https://www.youtube.com/embed/ZrQWEiVG6nU?rel=0",
            "lesson_plan": "משחק קצב: מוחאים כפיים ומקישים על הברכיים לסירוגין לפי קצב המנגינה."
        },
        {
            "id": "JCWSe0JShQI",
            "title": "נתופף על הגוף - מירב האוסמן",
            "url": "https://www.youtube.com/embed/JCWSe0JShQI?rel=0",
            "lesson_plan": "הפעלה בתנועה: הילדים מתפזרים במרחב. כשהמוזיקה עוצרת מבצעים 'פסל' בפוזה מצחיקה."
        },
        {
            "id": "FdjA3lrwwwY",
            "title": "בוקר טוב מירב האוסמן // חוויה מוסיקלית",
            "url": "https://www.youtube.com/embed/FdjA3lrwwwY?rel=0",
            "lesson_plan": "משחק קצב: מוחאים כפיים ומקישים על הברכיים לסירוגין לפי קצב המנגינה."
        },
        {
            "id": "fI-4nt3SUP0",
            "title": "מירב האוסמן - כמה טוב להתעמל",
            "url": "https://www.youtube.com/embed/fI-4nt3SUP0?rel=0",
            "lesson_plan": "הפעלה בתנועה: הילדים מתפזרים במרחב. כשהמוזיקה עוצרת מבצעים 'פסל' בפוזה מצחיקה."
        },
        {
            "id": "2VnBBzykxus",
            "title": "נקפוץ לגובה  מירב האוסמן // חוויה מוסיקלית",
            "url": "https://www.youtube.com/embed/2VnBBzykxus?rel=0",
            "lesson_plan": "משחק קצב: מוחאים כפיים ומקישים על הברכיים לסירוגין לפי קצב המנגינה."
        },
        {
            "id": "1EmZMylx3rY",
            "title": "מר רמזור - מירב האוסמן - זהירות בדרכים",
            "url": "https://www.youtube.com/embed/1EmZMylx3rY?rel=0",
            "lesson_plan": "משחק קצב: מוחאים כפיים ומקישים על הברכיים לסירוגין לפי קצב המנגינה."
        },
        {
            "id": "kWKnbiTd9II",
            "title": "אריאלה סביר התעמלות Ariela Savir",
            "url": "https://www.youtube.com/embed/kWKnbiTd9II?rel=0",
            "lesson_plan": "משחק קצב: מוחאים כפיים ומקישים על הברכיים לסירוגין לפי קצב המנגינה."
        },
        {
            "id": "u0l2nZD_k1o",
            "title": "שמש וענן - שיר לפתיחת הבוקר בגן הילדים - מירב האוסמן",
            "url": "https://www.youtube.com/embed/u0l2nZD_k1o?rel=0",
            "lesson_plan": "משחק קצב: מוחאים כפיים ומקישים על הברכיים לסירוגין לפי קצב המנגינה."
        },
        {
            "id": "bZQrxi5kso8",
            "title": "שירי משחק: הופ הופ הופ - ערוץ לולי",
            "url": "https://www.youtube.com/embed/bZQrxi5kso8?rel=0",
            "lesson_plan": "משחק קצב: מוחאים כפיים ומקישים על הברכיים לסירוגין לפי קצב המנגינה."
        },
        {
            "id": "6NNcnltRSnA",
            "title": "אריאלה סביר איפה הידיים Ariela Savir",
            "url": "https://www.youtube.com/embed/6NNcnltRSnA?rel=0",
            "lesson_plan": "הפעלה בתנועה: הילדים מתפזרים במרחב. כשהמוזיקה עוצרת מבצעים 'פסל' בפוזה מצחיקה."
        },
        {
            "id": "U1BW3qXuM38",
            "title": "שָׁלוֹם לָךְ שָׁנָה חֲדָשָׁה - מירב האוסמן",
            "url": "https://www.youtube.com/embed/U1BW3qXuM38?rel=0",
            "lesson_plan": "משחק קצב: מוחאים כפיים ומקישים על הברכיים לסירוגין לפי קצב המנגינה."
        },
        {
            "id": "73Pre2Shb6w",
            "title": "שיר החילזון - סרטון אנימציה קסום לילדים - מירב האוסמן",
            "url": "https://www.youtube.com/embed/73Pre2Shb6w?rel=0",
            "lesson_plan": "משחק קצב: מוחאים כפיים ומקישים על הברכיים לסירוגין לפי קצב המנגינה."
        }
    ],
    "israeli_classics": [
        {
            "id": "DpinVPmK8XI",
            "title": "שירי ילדים ברצף - מחרוזת שירי ילדות ישראלית 1 - ילדות ישראלית",
            "url": "https://www.youtube.com/embed/DpinVPmK8XI?rel=0",
            "lesson_plan": "שיח מורשת: משוחחים על השירים שגם אבא ואמא הכירו כשהיו קטנים ומצטרפים לשירה בציבור."
        },
        {
            "id": "jXKg-67KFKY",
            "title": "יחד כל הדרך! מחרוזת שירי ילדים ברצף - יחד ננצח - ילדות ישראלית",
            "url": "https://www.youtube.com/embed/jXKg-67KFKY?rel=0",
            "lesson_plan": "שיח מורשת: משוחחים על השירים שגם אבא ואמא הכירו כשהיו קטנים ומצטרפים לשירה בציבור."
        },
        {
            "id": "fgpGeo-e7jE",
            "title": "מחרוזת שיר נעמי שמר - שירים ברצף לילדים ולפעוטות",
            "url": "https://www.youtube.com/embed/fgpGeo-e7jE?rel=0",
            "lesson_plan": "שיח מורשת: משוחחים על השירים שגם אבא ואמא הכירו כשהיו קטנים ומצטרפים לשירה בציבור."
        },
        {
            "id": "qH3vXuajKF4",
            "title": "שירי ילדים ברצף - מחרוזת שירי ילדות ישראלית 2024 - ילדות ישראלית",
            "url": "https://www.youtube.com/embed/qH3vXuajKF4?rel=0",
            "lesson_plan": "שיח מורשת: משוחחים על השירים שגם אבא ואמא הכירו כשהיו קטנים ומצטרפים לשירה בציבור."
        },
        {
            "id": "AZEDyye4lHE",
            "title": "מחרוזת שירי ילדות ישראלית - שירי ילדים קטנים - שירי קטנטנים ברצף - ילדות ישראלית",
            "url": "https://www.youtube.com/embed/AZEDyye4lHE?rel=0",
            "lesson_plan": "שיח מורשת: משוחחים על השירים שגם אבא ואמא הכירו כשהיו קטנים ומצטרפים לשירה בציבור."
        },
        {
            "id": "D8bU9luKx0A",
            "title": "מחרוזת שירי ילדות ישראלית - שירי ילדים קטנים - שירי קטנטנים ברצף - ילדות ישראלית",
            "url": "https://www.youtube.com/embed/D8bU9luKx0A?rel=0",
            "lesson_plan": "שיח מורשת: משוחחים על השירים שגם אבא ואמא הכירו כשהיו קטנים ומצטרפים לשירה בציבור."
        },
        {
            "id": "9ujZ_SeN8Uk",
            "title": "השירים שהכי כיף לרקוד איתם -שירי ילדות ישראלית-  ילדות ישראלית",
            "url": "https://www.youtube.com/embed/9ujZ_SeN8Uk?rel=0",
            "lesson_plan": "שיח מורשת: משוחחים על השירים שגם אבא ואמא הכירו כשהיו קטנים ומצטרפים לשירה בציבור."
        },
        {
            "id": "YMLsE_DMPGQ",
            "title": "מחרוזת שירי עוזי חיטמן - שירים לילדים ופעוטות בילדות ישראלית",
            "url": "https://www.youtube.com/embed/YMLsE_DMPGQ?rel=0",
            "lesson_plan": "שיח מורשת: משוחחים על השירים שגם אבא ואמא הכירו כשהיו קטנים ומצטרפים לשירה בציבור."
        },
        {
            "id": "sF3pmyiTCfU",
            "title": "ספיישל שירים ודקלומים לקטנטנים לפני השינה -  ילדות ישראלית",
            "url": "https://www.youtube.com/embed/sF3pmyiTCfU?rel=0",
            "lesson_plan": "שיח מורשת: משוחחים על השירים שגם אבא ואמא הכירו כשהיו קטנים ומצטרפים לשירה בציבור."
        },
        {
            "id": "nOdNMzf5cik",
            "title": "מחרוזת שירים וצבעים - שירי קטנטנים ברצף - כך נולד הצבע, יש לי קוביות ועוד -  ילדות ישראלית",
            "url": "https://www.youtube.com/embed/nOdNMzf5cik?rel=0",
            "lesson_plan": "שיח מורשת: משוחחים על השירים שגם אבא ואמא הכירו כשהיו קטנים ומצטרפים לשירה בציבור."
        },
        {
            "id": "EEb8d96WP5s",
            "title": "שירי ילדים שמחים - מחרוזת שירים שמחים ברצף - ילדות ישראלית",
            "url": "https://www.youtube.com/embed/EEb8d96WP5s?rel=0",
            "lesson_plan": "שיח מורשת: משוחחים על השירים שגם אבא ואמא הכירו כשהיו קטנים ומצטרפים לשירה בציבור."
        },
        {
            "id": "44LEkcNoxRA",
            "title": "מסיבת ישראלית - שירי ילדים קטנים - שירי קטנטנים ברצף - יום העצמאות - ילדות ישראלית",
            "url": "https://www.youtube.com/embed/44LEkcNoxRA?rel=0",
            "lesson_plan": "שיח מורשת: משוחחים על השירים שגם אבא ואמא הכירו כשהיו קטנים ומצטרפים לשירה בציבור."
        }
    ],
    "relaxation_sleep": [
        {
            "id": "ZD6OXOEQ5Sw",
            "title": "מחרוזת שירים שקטים ורגועים - שירים ברצף - ילדות ישראלית",
            "url": "https://www.youtube.com/embed/ZD6OXOEQ5Sw?rel=0",
            "lesson_plan": "דמיון מודרך עדין: שוכבים בנוח ומדמיינים שאנחנו ענן שט בשמיים לפי צלילי הפסנתר."
        },
        {
            "id": "WNxp6vhlD3Y",
            "title": "מוזיקה מרגיעה - מנגינה מרגיעה",
            "url": "https://www.youtube.com/embed/WNxp6vhlD3Y?rel=0",
            "lesson_plan": "דמיון מודרך עדין: שוכבים בנוח ומדמיינים שאנחנו ענן שט בשמיים לפי צלילי הפסנתר."
        },
        {
            "id": "50vkaIsJn9c",
            "title": "מוזיקה מרגיעה לבוקר",
            "url": "https://www.youtube.com/embed/50vkaIsJn9c?rel=0",
            "lesson_plan": "זמן רגיעה: מכבים את האורות בחדר. הילדים שוכבים בעיניים עצומות ומתרגלים נשימות עמוקות עם המוזיקה."
        },
        {
            "id": "_AFjGSVTPBA",
            "title": "מוזיקה מרגיעה יפיפייה עם צלילי מים - מנגינה מרגיעה לכל פעילות, מוזיקה מרגיעה לשינה, נעימות מרגיעות",
            "url": "https://www.youtube.com/embed/_AFjGSVTPBA?rel=0",
            "lesson_plan": "דמיון מודרך עדין: שוכבים בנוח ומדמיינים שאנחנו ענן שט בשמיים לפי צלילי הפסנתר."
        },
        {
            "id": "LTleKozCYaY",
            "title": "מוזיקה מרגיעה לתינוקות 🍼 מנגינה מרגיעה לתינוקות עייפים או חסרי מנוחה 🌙 Baby Sleep Music",
            "url": "https://www.youtube.com/embed/LTleKozCYaY?rel=0",
            "lesson_plan": "דמיון מודרך עדין: שוכבים בנוח ומדמיינים שאנחנו ענן שט בשמיים לפי צלילי הפסנתר."
        },
        {
            "id": "gQN4MffoYAQ",
            "title": "רצף של ניגוני חבד שקטים במשך 3 שעות!!!",
            "url": "https://www.youtube.com/embed/gQN4MffoYAQ?rel=0",
            "lesson_plan": "זמן רגיעה: מכבים את האורות בחדר. הילדים שוכבים בעיניים עצומות ומתרגלים נשימות עמוקות עם המוזיקה."
        },
        {
            "id": "myULyHvYkGc",
            "title": "מוזיקה מרגיעה - נעימות פסנתר שקטות ומרגיעות",
            "url": "https://www.youtube.com/embed/myULyHvYkGc?rel=0",
            "lesson_plan": "זמן רגיעה: מכבים את האורות בחדר. הילדים שוכבים בעיניים עצומות ומתרגלים נשימות עמוקות עם המוזיקה."
        },
        {
            "id": "sneo_ZC1GR4",
            "title": "🌊 מוזיקה להפחתת סטרס ולניקוי מחשבות ♫ צלילי אקווריום מרגיעים ודגים 🐟 מוזיקה לשינה עמוקה",
            "url": "https://www.youtube.com/embed/sneo_ZC1GR4?rel=0",
            "lesson_plan": "זמן רגיעה: מכבים את האורות בחדר. הילדים שוכבים בעיניים עצומות ומתרגלים נשימות עמוקות עם המוזיקה."
        },
        {
            "id": "ol4hCKvg1_0",
            "title": "מוזיקה מרגיעה ומרפאה עם גלי אלפא לשחרור מתח נפשי ופיזי, לרגיעה, שינה עמוקה 🌙 מוזיקה למדיטציה",
            "url": "https://www.youtube.com/embed/ol4hCKvg1_0?rel=0",
            "lesson_plan": "זמן רגיעה: מכבים את האורות בחדר. הילדים שוכבים בעיניים עצומות ומתרגלים נשימות עמוקות עם המוזיקה."
        },
        {
            "id": "wJLLRKu2Qsw",
            "title": "מוזיקה מרגיעה ללמידה, ריכוז ועבודה ♫ נעימה מרגיעה ללימודים ❤ מרגיע ומעודד ריכוז, מוזיקה ללימודים",
            "url": "https://www.youtube.com/embed/wJLLRKu2Qsw?rel=0",
            "lesson_plan": "זמן רגיעה: מכבים את האורות בחדר. הילדים שוכבים בעיניים עצומות ומתרגלים נשימות עמוקות עם המוזיקה."
        },
        {
            "id": "J0b8KLqijm4",
            "title": "מחרוזת שירי סתיו - שירים ברצף - ילדות ישראלית",
            "url": "https://www.youtube.com/embed/J0b8KLqijm4?rel=0",
            "lesson_plan": "דמיון מודרך עדין: שוכבים בנוח ומדמיינים שאנחנו ענן שט בשמיים לפי צלילי הפסנתר."
        },
        {
            "id": "DWtSWvxI8S8",
            "title": "שירים שקטים",
            "url": "https://www.youtube.com/embed/DWtSWvxI8S8?rel=0",
            "lesson_plan": "זמן רגיעה: מכבים את האורות בחדר. הילדים שוכבים בעיניים עצומות ומתרגלים נשימות עמוקות עם המוזיקה."
        }
    ],
    "story_time": [
        {
            "id": "8GYi8oCAp_0",
            "title": "תרנגולת נבונה",
            "url": "https://www.youtube.com/embed/8GYi8oCAp_0?rel=0",
            "lesson_plan": "ציור סיפור: נבקש מהילדים לצייר את הדמות המועדפת עליהם מהסיפור שראינו."
        },
        {
            "id": "A6tvkBGPCd8",
            "title": "סינדרלה - סיפור לילדים לפני השינה",
            "url": "https://www.youtube.com/embed/A6tvkBGPCd8?rel=0",
            "lesson_plan": "ציור סיפור: נבקש מהילדים לצייר את הדמות המועדפת עליהם מהסיפור שראינו."
        },
        {
            "id": "RUXbWlosgsM",
            "title": "סיפור לילדים לפני השינה בעברית מעשה בשני דובים רעבים 🐻🐻",
            "url": "https://www.youtube.com/embed/RUXbWlosgsM?rel=0",
            "lesson_plan": "ציור סיפור: נבקש מהילדים לצייר את הדמות המועדפת עליהם מהסיפור שראינו."
        },
        {
            "id": "bRQn4EYbx9w",
            "title": "שלושת החזירונים✨ אגדת ילדים 🧸 סיפורים לפני השינה",
            "url": "https://www.youtube.com/embed/bRQn4EYbx9w?rel=0",
            "lesson_plan": "דיון בעקבות הסיפור: לאחר הצפייה, נשאל את הילדים - מה היה הרגע שהכי אהבתם? ואיך הגיבור הרגיש?"
        },
        {
            "id": "0JyNRdvxgUw",
            "title": "האריה שאהב תות 🍓🦁 The Lion That Loved Strawberries",
            "url": "https://www.youtube.com/embed/0JyNRdvxgUw?rel=0",
            "lesson_plan": "דיון בעקבות הסיפור: לאחר הצפייה, נשאל את הילדים - מה היה הרגע שהכי אהבתם? ואיך הגיבור הרגיש?"
        },
        {
            "id": "bjE9d_EF55A",
            "title": "ילד דרקון - סיפור על חברות ואומץ",
            "url": "https://www.youtube.com/embed/bjE9d_EF55A?rel=0",
            "lesson_plan": "ציור סיפור: נבקש מהילדים לצייר את הדמות המועדפת עליהם מהסיפור שראינו."
        },
        {
            "id": "NpJRM-Jt4sk",
            "title": "טרופותי",
            "url": "https://www.youtube.com/embed/NpJRM-Jt4sk?rel=0",
            "lesson_plan": "ציור סיפור: נבקש מהילדים לצייר את הדמות המועדפת עליהם מהסיפור שראינו."
        },
        {
            "id": "Xq618AEBS7A",
            "title": "סרטים חינוכיים לילדים",
            "url": "https://www.youtube.com/embed/Xq618AEBS7A?rel=0",
            "lesson_plan": "דיון בעקבות הסיפור: לאחר הצפייה, נשאל את הילדים - מה היה הרגע שהכי אהבתם? ואיך הגיבור הרגיש?"
        },
        {
            "id": "CdH7ihsDycI",
            "title": "הסיפור הכי משעמם בעולם! סיפור לילדים לפני השינה (סיפורים לפני השינה בעברית)",
            "url": "https://www.youtube.com/embed/CdH7ihsDycI?rel=0",
            "lesson_plan": "ציור סיפור: נבקש מהילדים לצייר את הדמות המועדפת עליהם מהסיפור שראינו."
        },
        {
            "id": "yBpT1_OFrMc",
            "title": "הנסיכה רפונזל – סיפור לילדים",
            "url": "https://www.youtube.com/embed/yBpT1_OFrMc?rel=0",
            "lesson_plan": "דיון בעקבות הסיפור: לאחר הצפייה, נשאל את הילדים - מה היה הרגע שהכי אהבתם? ואיך הגיבור הרגיש?"
        },
        {
            "id": "F0pMD35ifHg",
            "title": "מר הפוך - ניר פרידמן מספר",
            "url": "https://www.youtube.com/embed/F0pMD35ifHg?rel=0",
            "lesson_plan": "דיון בעקבות הסיפור: לאחר הצפייה, נשאל את הילדים - מה היה הרגע שהכי אהבתם? ואיך הגיבור הרגיש?"
        },
        {
            "id": "UuInsSwfivI",
            "title": "הפיל שרצה להיות הכי - הסרט המלא",
            "url": "https://www.youtube.com/embed/UuInsSwfivI?rel=0",
            "lesson_plan": "דיון בעקבות הסיפור: לאחר הצפייה, נשאל את הילדים - מה היה הרגע שהכי אהבתם? ואיך הגיבור הרגיש?"
        }
    ]
}